funapi/__init__.py
funworker-0.0.1.dist-info/LICENSE
funworker-0.0.1.dist-info/METADATA
funworker-0.0.1.dist-info/WHEEL
funworker-0.0.1.dist-info/entry_points.txt
funworker-0.0.1.dist-info/top_level.txt
funworker-0.0.1.dist-info/RECORD
