Metadata-Version: 2.1
Name: funworker
Version: 0.0.1
Summary: funworker
Home-page: https://github.com/farfarfun/funworker
Author: bingtao
Author-email: 1007530194@qq.com
License-File: LICENSE
Requires-Dist: funpypi
Requires-Dist: funfile
Requires-Dist: requests
Requires-Dist: tqdm
